{
  "id": 22719,
  "name": "Weekday",
  "slug": "weekday",
  "former_names": [],
  "small_logo_thumb_url": "https://bookface-images.s3.amazonaws.com/small_logos/abebec09c171112b2f825b920689d4885969573a.png",
  "website": "https://weekday.works/",
  "all_locations": "Bengaluru, KA, India; Remote",
  "long_description": "We help companies hire by building a highly curated list of engineering candidates for them; crowdsourced by our network of software engineers who moonlight as “mini-recruiters” or scouts. Our product enables anyone to become that scout and earn passive income.\r\n",
  "one_liner": "Hire engineers vouched by other techies",
  "team_size": 20,
  "industry": "B2B",
  "subindustry": "B2B -> Recruiting and Talent",
  "launched_at": 1614838352,
  "tags": [
    "B2B",
    "Recruiting"
  ],
  "tags_highlighted": [],
  "top_company": false,
  "isHiring": true,
  "nonprofit": false,
  "batch": "W21",
  "status": "Active",
  "industries": [
    "B2B",
    "Recruiting and Talent"
  ],
  "regions": [
    "India",
    "South Asia",
    "Remote",
    "Fully Remote"
  ],
  "stage": "Early",
  "app_video_public": false,
  "demo_day_video_public": false,
  "app_answers": null,
  "question_answers": false,
  "url": "https://www.ycombinator.com/companies/weekday",
  "api": "https://yc-oss.github.io/api/batches/w21/weekday.json"
}
