{
  "id": 25866,
  "name": "Ponyrun",
  "slug": "ponyrun",
  "former_names": [
    "Asparagus",
    "Nimbus"
  ],
  "small_logo_thumb_url": "https://bookface-images.s3.amazonaws.com/small_logos/4a6aa11f944dc1a5cb37880b3a981988db91d193.png",
  "website": "http://www.ponyrun.ai",
  "all_locations": "San Francisco, CA, USA; Remote",
  "long_description": "Ponyrun evaluates people for you. We help you answer questions like: Should you sell to them? Are they a good fit for your product? Should you interview them? \r\n\r\nIts easy to use. Give it a search URL or a list of people. Tell Ponyrun what you want to evaluate the person on. And Ponyrun will go through the person's information (e.g. LinkedIn), and evaluate them.",
  "one_liner": "Automate prospect research at scale",
  "team_size": 3,
  "industry": "B2B",
  "subindustry": "B2B -> Operations",
  "launched_at": 1644859951,
  "tags": [
    "Analytics",
    "Sales",
    "Operations",
    "AI",
    "AI Assistant"
  ],
  "tags_highlighted": [],
  "top_company": false,
  "isHiring": false,
  "nonprofit": false,
  "batch": "Winter 2022",
  "status": "Active",
  "industries": [
    "B2B",
    "Operations"
  ],
  "regions": [
    "United States of America",
    "America / Canada",
    "Remote",
    "Fully Remote"
  ],
  "stage": "Early",
  "app_video_public": false,
  "demo_day_video_public": false,
  "app_answers": null,
  "question_answers": false,
  "url": "https://www.ycombinator.com/companies/ponyrun",
  "api": "https://yc-oss.github.io/api/batches/winter-2022/ponyrun.json"
}
