{
  "id": 26053,
  "name": "Powerhouse AI",
  "slug": "powerhouse-ai",
  "former_names": [],
  "small_logo_thumb_url": "https://bookface-images.s3.amazonaws.com/small_logos/22014ae42b07dcdd7cfa478d98496b4ded0b0230.png",
  "website": "https://www.powerhouseai.com",
  "all_locations": "Singapore, Singapore",
  "long_description": "Powerhouse AI offers automation at a fraction of the cost of regular automation solutions. Enabling warehouses to become more competitive, fast. \r\n\r\n\r\n- How? By making warehousing as easy as taking pictures with a mobile device; digitizing processes and using the power of the camera to automate counting and checking tasks.\r\n\r\n\r\nFour core functionality areas:\r\n\r\n- Workflow Digitization: simplify and automate warehousing with AI powered workflows. \r\n- AI Counting: automate the tedious and error-prone counting of inventory. \r\n- AI Label Processing: scan everything [not just barcodes]. Fast. \r\n- AI Document Processing: reading logistics documents with the click of a button.  \r\n\r\n\r\nCore benefits: de-risking and future-proofing your warehouse operations \r\n\r\n- Increasing efficiency and accuracy with 20% to 40%\r\n- State-of-the-art technology\r\n- Making “dumb” boxes smart \r\n- Easily deal with supplier data inconsistencies \r\n- Enabling a data driven way of working \r\n- Real-time access to data ",
  "one_liner": "Vision-powered warehouse automation: maximizing performance and value",
  "team_size": 6,
  "industry": "B2B",
  "subindustry": "B2B -> Supply Chain and Logistics",
  "launched_at": 1643089929,
  "tags": [
    "SaaS",
    "Warehouse Management Tech",
    "Logistics"
  ],
  "tags_highlighted": [],
  "top_company": false,
  "isHiring": false,
  "nonprofit": false,
  "batch": "Winter 2022",
  "status": "Active",
  "industries": [
    "B2B",
    "Supply Chain and Logistics"
  ],
  "regions": [
    "Singapore",
    "Southeast Asia",
    "Remote",
    "Partly Remote"
  ],
  "stage": "Early",
  "app_video_public": false,
  "demo_day_video_public": false,
  "app_answers": null,
  "question_answers": false,
  "url": "https://www.ycombinator.com/companies/powerhouse-ai",
  "api": "https://yc-oss.github.io/api/batches/winter-2022/powerhouse-ai.json"
}
