{
  "id": 30942,
  "name": "Scott AI",
  "slug": "scott-ai",
  "former_names": [
    "Juno",
    "Scott AI",
    "Juno"
  ],
  "small_logo_thumb_url": "https://bookface-images.s3.amazonaws.com/small_logos/e147d1eb5a08ce6e087e44a2f10d637816c7c5db.png",
  "website": "https://tryscott.ai",
  "all_locations": "NY, USA",
  "long_description": "Coding agents made writing code fast. But 6 engineers in a room will probably still disagree on what needs to be built.\r\n\r\nScott AI is a planning workspace where engineering teams align on what to build before their coding agents start building it.",
  "one_liner": "The planning layer for teams that build with coding agents",
  "team_size": 3,
  "industry": "B2B",
  "subindustry": "B2B",
  "launched_at": 1762199813,
  "tags": [],
  "tags_highlighted": [],
  "top_company": false,
  "isHiring": true,
  "nonprofit": false,
  "batch": "Fall 2025",
  "status": "Active",
  "industries": [
    "B2B"
  ],
  "regions": [
    "United States of America",
    "America / Canada"
  ],
  "stage": "Early",
  "app_video_public": false,
  "demo_day_video_public": false,
  "app_answers": null,
  "question_answers": false,
  "url": "https://www.ycombinator.com/companies/scott-ai",
  "api": "https://yc-oss.github.io/api/batches/fall-2025/scott-ai.json"
}
