{
  "id": 24136,
  "name": "MadEats",
  "slug": "madeats",
  "former_names": [],
  "small_logo_thumb_url": "https://bookface-images.s3.amazonaws.com/small_logos/da7ac5641874c143a5cbbb11415e9ddf6446888f.png",
  "website": "",
  "all_locations": "Makati, NCR, Philippines",
  "long_description": "MadEats is an online delivery-only restaurant group in the Philippines, building affordable, high margin food brands by using our own ghost kitchens. \r\n\r\nSince we use ghost kitchens, we don’t have to spend for expensive dining areas and wait staff. We can spend more money on growing our food brands, better food, and making better delivery experiences.\r\n",
  "one_liner": "Online delivery-only restaurant group in the Philippines",
  "team_size": null,
  "industry": "Consumer",
  "subindustry": "Consumer -> Food and Beverage",
  "launched_at": 1627559016,
  "tags": [
    "Ghost Kitchens",
    "E-commerce"
  ],
  "tags_highlighted": [],
  "top_company": false,
  "isHiring": false,
  "nonprofit": false,
  "batch": "Summer 2021",
  "status": "Acquired",
  "industries": [
    "Consumer",
    "Food and Beverage"
  ],
  "regions": [
    "Philippines",
    "Southeast Asia",
    "Remote",
    "Partly Remote"
  ],
  "stage": "Early",
  "app_video_public": false,
  "demo_day_video_public": false,
  "app_answers": null,
  "question_answers": false,
  "url": "https://www.ycombinator.com/companies/madeats",
  "api": "https://yc-oss.github.io/api/batches/summer-2021/madeats.json"
}
