{
  "id": 12452,
  "name": "Vizy",
  "slug": "vizy",
  "former_names": [
    "Clay",
    "Carve"
  ],
  "small_logo_thumb_url": "https://bookface-images.s3.amazonaws.com/small_logos/c1c71990fe722fb0c0aa37cc11fe987f9119b30e.png",
  "website": "http://vizy.io",
  "all_locations": "San Francisco, CA, USA",
  "long_description": "A cross-platform, click-to-talk collaboration tool with features like NLP-powered transcription, screen sharing, multiplayer app collaboration, voice and video channels, and file sharing.",
  "one_liner": "An all-in-one virtual office for remote teams",
  "team_size": 3,
  "industry": "Consumer",
  "subindustry": "Consumer -> Transportation Services",
  "launched_at": 1551145972,
  "tags": [
    "SaaS"
  ],
  "tags_highlighted": [],
  "top_company": false,
  "isHiring": false,
  "nonprofit": false,
  "batch": "S19",
  "status": "Inactive",
  "industries": [
    "Consumer",
    "Transportation Services"
  ],
  "regions": [
    "United States of America",
    "America / Canada",
    "Remote",
    "Partly Remote"
  ],
  "stage": "Early",
  "app_video_public": false,
  "demo_day_video_public": false,
  "app_answers": null,
  "question_answers": false,
  "url": "https://www.ycombinator.com/companies/vizy",
  "api": "https://yc-oss.github.io/api/batches/s19/vizy.json"
}
