{
  "id": 30464,
  "name": "Sixtyfour",
  "slug": "sixtyfour",
  "former_names": [
    "Sixtyfour",
    "Sixtyfour AI"
  ],
  "small_logo_thumb_url": "https://bookface-images.s3.amazonaws.com/small_logos/7a94c5b6ca35db4a8ecda083bd02671f8be5393f.png",
  "website": "https://www.sixtyfour.ai/",
  "all_locations": "San Francisco, CA, USA",
  "long_description": "Instantly deploy custom research agents to source and enrich specialized professionals, company data, and insights directly into your existing systems.",
  "one_liner": "People Intelligence at Scale",
  "team_size": 8,
  "industry": "B2B",
  "subindustry": "B2B -> Operations",
  "launched_at": 1747432267,
  "tags": [
    "Artificial Intelligence",
    "Sales",
    "Sales Enablement",
    "Operations"
  ],
  "tags_highlighted": [],
  "top_company": false,
  "isHiring": true,
  "nonprofit": false,
  "batch": "Spring 2025",
  "status": "Active",
  "industries": [
    "B2B",
    "Operations"
  ],
  "regions": [
    "United States of America",
    "America / Canada"
  ],
  "stage": "Early",
  "app_video_public": false,
  "demo_day_video_public": false,
  "app_answers": null,
  "question_answers": false,
  "url": "https://www.ycombinator.com/companies/sixtyfour",
  "api": "https://yc-oss.github.io/api/batches/spring-2025/sixtyfour.json"
}
