{
  "id": 1911,
  "name": "Contrast",
  "slug": "contrast",
  "former_names": [
    "Toybox"
  ],
  "small_logo_thumb_url": "https://bookface-images.s3.amazonaws.com/small_logos/508f1978cc2dc172474c547c73cf0b9d8fd91bb0.png",
  "website": "https://mismatch.app/",
  "all_locations": "New York, NY, USA",
  "long_description": "It's a better way to build frontend. It connects your Stories, Tokens, & Figma components. It lets you inspect designs with confidence and speed. And you can use it in Storybook.",
  "one_liner": "Developer Handoff - Reimagined for Storybook",
  "team_size": 4,
  "industry": "B2B",
  "subindustry": "B2B -> Engineering, Product and Design",
  "launched_at": 1524708159,
  "tags": [
    "Developer Tools"
  ],
  "tags_highlighted": [],
  "top_company": false,
  "isHiring": false,
  "nonprofit": false,
  "batch": "Summer 2018",
  "status": "Inactive",
  "industries": [
    "B2B",
    "Engineering, Product and Design"
  ],
  "regions": [
    "United States of America",
    "America / Canada",
    "Remote",
    "Partly Remote"
  ],
  "stage": "Early",
  "app_video_public": false,
  "demo_day_video_public": false,
  "app_answers": null,
  "question_answers": false,
  "url": "https://www.ycombinator.com/companies/contrast",
  "api": "https://yc-oss.github.io/api/batches/summer-2018/contrast.json"
}
