{
  "id": 215,
  "name": "Crocodoc",
  "slug": "crocodoc",
  "former_names": [],
  "small_logo_thumb_url": "https://bookface-images.s3.amazonaws.com/small_logos/934b28e2d4367fc33767785a5a2414ea7c0783b5.png",
  "website": "https://crocodoc.com",
  "all_locations": "San Francisco, CA, USA",
  "long_description": "Crocodoc developed the world's most advanced web-based document viewing and collaboration technology for Microsoft Office and PDF files, built on open standards such as HTML5 and CSS3.\r\n\r\nWhether viewing a document, adding comments to a presentation, highlighting an e-textbook, or filling out a form, we make it easy for companies to create amazing experiences for their users with technology that is secure, scalable, and trusted by top brands in the consumer and enterprise space.\r\n\r\nEvery month users upload millions of documents to Crocodoc, whose customers include top brands such as Dropbox, Yammer, LinkedIn, SAP, and Edmodo.\r\n\r\nCrocodoc was founded in 2007 and is funded by Y Combinator, SV Angel, 500 Startups, and top angel investors including Joshua Schachter, Paul Buchheit, Steve Chen, and Shan Sinha.",
  "one_liner": "Embed PDFs, PowerPoints, and other documents into web and mobile apps",
  "team_size": 0,
  "industry": "B2B",
  "subindustry": "B2B -> Engineering, Product and Design",
  "launched_at": 1326790370,
  "tags": [
    "Documents",
    "SaaS"
  ],
  "tags_highlighted": [],
  "top_company": false,
  "isHiring": false,
  "nonprofit": false,
  "batch": "Winter 2010",
  "status": "Acquired",
  "industries": [
    "B2B",
    "Engineering, Product and Design"
  ],
  "regions": [
    "United States of America",
    "America / Canada"
  ],
  "stage": "Early",
  "app_video_public": false,
  "demo_day_video_public": false,
  "app_answers": null,
  "question_answers": false,
  "url": "https://www.ycombinator.com/companies/crocodoc",
  "api": "https://yc-oss.github.io/api/batches/winter-2010/crocodoc.json"
}
