{
  "id": 13532,
  "name": "Living Carbon",
  "slug": "living-carbon",
  "former_names": [],
  "small_logo_thumb_url": "https://bookface-images.s3.amazonaws.com/small_logos/15bec4a7b933065121458477f9bf67ed7382b11f.png",
  "website": "https://www.livingcarbon.com",
  "all_locations": "Charleston, SC, USA",
  "long_description": "transforming degraded land into high quality environmental assets using end to end operational expertise and precision breeding.",
  "one_liner": "maximizing biomass on low quality land",
  "team_size": 40,
  "industry": "Industrials",
  "subindustry": "Industrials -> Climate",
  "launched_at": 1628292917,
  "tags": [
    "Synthetic Biology",
    "Biotech",
    "Climate",
    "Agriculture"
  ],
  "tags_highlighted": [],
  "top_company": false,
  "isHiring": true,
  "nonprofit": false,
  "batch": "Winter 2020",
  "status": "Active",
  "industries": [
    "Industrials",
    "Climate"
  ],
  "regions": [
    "United States of America",
    "America / Canada",
    "Remote",
    "Partly Remote"
  ],
  "stage": "Early",
  "app_video_public": false,
  "demo_day_video_public": false,
  "app_answers": null,
  "question_answers": false,
  "url": "https://www.ycombinator.com/companies/living-carbon",
  "api": "https://yc-oss.github.io/api/batches/winter-2020/living-carbon.json"
}
