{
  "id": 332,
  "name": "ContestMachine",
  "slug": "contestmachine",
  "former_names": [],
  "small_logo_thumb_url": "/company/thumb/missing.png",
  "website": "http://contestmachine.com",
  "all_locations": "Southfield, MI, USA",
  "long_description": "ContestMachine is a web service that makes running promotions from any website easy. The service allows clients to run a contest or giveaway from their blog or website and handles the rest of the details, like collecting submissions and contacting winners. The service also allows clients varied options, like choosing entry requirements, start and end times, and the addition of prizes.",
  "one_liner": "Roll your own contest or giveaway.  No longer in business.",
  "team_size": 2,
  "industry": "B2B",
  "subindustry": "B2B -> Marketing",
  "launched_at": 1326791384,
  "tags": [
    "Marketing"
  ],
  "tags_highlighted": [],
  "top_company": false,
  "isHiring": false,
  "nonprofit": false,
  "batch": "S07",
  "status": "Inactive",
  "industries": [
    "B2B",
    "Marketing"
  ],
  "regions": [
    "United States of America",
    "America / Canada"
  ],
  "stage": "Early",
  "app_video_public": false,
  "demo_day_video_public": false,
  "app_answers": null,
  "question_answers": false,
  "url": "https://www.ycombinator.com/companies/contestmachine",
  "api": "https://yc-oss.github.io/api/batches/s07/contestmachine.json"
}
