{
  "id": 1856,
  "name": "Culture Biosciences",
  "slug": "culture-biosciences",
  "former_names": [
    "Culture Robotics"
  ],
  "small_logo_thumb_url": "https://bookface-images.s3.amazonaws.com/small_logos/ac962091728b8d8d331a854791fa1b892cb9f93f.png",
  "website": "https://culturebiosciences.com",
  "all_locations": "South San Francisco, CA, USA",
  "long_description": "Culture Biosciences grows cells for biotech companies.  Our customers genetically modify organisms to produce new therapeutics, materials, fuels and foods. We help them quickly run experiments and  develop manufacturing processes so they can get their products to market faster. We've built proprietary software and automation systems to make operating our bioreactors more efficient than existing systems. We also provide customers with new software tools that help them analyze and contextualize their data. We are currently serving a number of biotech customers and scaling out our infrastructure.\r\n",
  "one_liner": "We grow cells for biotech companies.",
  "team_size": 40,
  "industry": "Healthcare",
  "subindustry": "Healthcare -> Industrial Bio",
  "launched_at": 1511233372,
  "tags": [
    "Cellular Agriculture",
    "Biotech"
  ],
  "tags_highlighted": [],
  "top_company": false,
  "isHiring": false,
  "nonprofit": false,
  "batch": "Winter 2018",
  "status": "Active",
  "industries": [
    "Healthcare",
    "Industrial Bio"
  ],
  "regions": [
    "United States of America",
    "America / Canada",
    "Remote",
    "Partly Remote"
  ],
  "stage": "Growth",
  "app_video_public": false,
  "demo_day_video_public": false,
  "app_answers": null,
  "question_answers": false,
  "url": "https://www.ycombinator.com/companies/culture-biosciences",
  "api": "https://yc-oss.github.io/api/batches/winter-2018/culture-biosciences.json"
}
