{
  "id": 12005,
  "name": "Demodesk",
  "slug": "demodesk",
  "former_names": [],
  "small_logo_thumb_url": "https://bookface-images.s3.amazonaws.com/small_logos/20c74945d30965bb5d2101fd68ae3e99cc624985.png",
  "website": "https://demodesk.com",
  "all_locations": "Munich, BY, Germany",
  "long_description": "Demodesk provides AI-powered sales meeting software that summarizes your calls, automates CRM management, and delivers personalized, actionable sales coaching.",
  "one_liner": "AI-powered sales coaching",
  "team_size": 25,
  "industry": "B2B",
  "subindustry": "B2B -> Sales",
  "launched_at": 1541473397,
  "tags": [
    "SaaS",
    "B2B",
    "Sales",
    "Video",
    "AI"
  ],
  "tags_highlighted": [],
  "top_company": false,
  "isHiring": false,
  "nonprofit": false,
  "batch": "Winter 2019",
  "status": "Active",
  "industries": [
    "B2B",
    "Sales"
  ],
  "regions": [
    "Germany",
    "Europe",
    "Remote",
    "Partly Remote"
  ],
  "stage": "Growth",
  "app_video_public": true,
  "demo_day_video_public": true,
  "app_answers": true,
  "question_answers": true,
  "url": "https://www.ycombinator.com/companies/demodesk",
  "api": "https://yc-oss.github.io/api/batches/winter-2019/demodesk.json"
}
