{
  "id": 616,
  "name": "Pushbullet",
  "slug": "pushbullet",
  "former_names": [
    "PushBullet"
  ],
  "small_logo_thumb_url": "https://bookface-images.s3.amazonaws.com/small_logos/5851e5656bbd2bdef010bd1269d6252d9748475b.png",
  "website": "https://www.pushbullet.com",
  "all_locations": "San Francisco, CA, USA; Remote",
  "long_description": "Pushbullet connects your devices, making it easy and automatic to share almost anything between them.\r\n\r\nOur mission is to bridge the gap between your phone, tablet, and computer, enabling them to work better together.\r\n\r\nWhy is this important? Simple: in the past few years, smartphones and tablets have taken over people's digital lives. Sharing data between them and with computers, however, can be a real pain. We make it easy and automatic.",
  "one_liner": "Push things to your other things.",
  "team_size": 3,
  "industry": "Consumer",
  "subindustry": "Consumer -> Home and Personal",
  "launched_at": 1384978974,
  "tags": [
    "Notifications"
  ],
  "tags_highlighted": [],
  "top_company": false,
  "isHiring": false,
  "nonprofit": false,
  "batch": "W14",
  "status": "Active",
  "industries": [
    "Consumer",
    "Home and Personal"
  ],
  "regions": [
    "United States of America",
    "America / Canada",
    "Remote",
    "Fully Remote"
  ],
  "stage": "Early",
  "app_video_public": false,
  "demo_day_video_public": false,
  "app_answers": null,
  "question_answers": false,
  "url": "https://www.ycombinator.com/companies/pushbullet",
  "api": "https://yc-oss.github.io/api/batches/w14/pushbullet.json"
}
