{
  "id": 29297,
  "name": "Eggnog",
  "slug": "eggnog",
  "former_names": [],
  "small_logo_thumb_url": "https://bookface-images.s3.amazonaws.com/small_logos/b8db4ae69ffa9fe27a2e056c7825fa07368367d7.png",
  "website": "https://www.eggnog.ai",
  "all_locations": "New York, NY, USA",
  "long_description": "Eggnog is the Youtube for AI-generated content. The initial product is the only AI video platform on the market that generates consistent characters. The vision is to have the largest library of remixable characters and sets for users to collaboratively build and watch AI-generated content. Eggnog launched a week ago, and videos made on the platform are getting 100k views on Twitter.\r\n\r\nTeam: Sam (BS, Applied Math from Harvard) was a data scientist at Facebook and Quora working on newsfeed and creator monetization. Jitesh (BS, MEng from MIT CS) was a consultant at McKinsey and PM at Flexport. \r\n",
  "one_liner": "Youtube for AI-generated content",
  "team_size": 2,
  "industry": "Consumer",
  "subindustry": "B2B",
  "launched_at": 1710803454,
  "tags": [
    "Artificial Intelligence",
    "Entertainment",
    "Social Media",
    "Video"
  ],
  "tags_highlighted": [],
  "top_company": false,
  "isHiring": false,
  "nonprofit": false,
  "batch": "W24",
  "status": "Active",
  "industries": [
    "Consumer"
  ],
  "regions": [
    "United States of America",
    "America / Canada"
  ],
  "stage": "Early",
  "app_video_public": false,
  "demo_day_video_public": false,
  "app_answers": null,
  "question_answers": false,
  "url": "https://www.ycombinator.com/companies/eggnog",
  "api": "https://yc-oss.github.io/api/batches/w24/eggnog.json"
}
