{
  "id": 29278,
  "name": "Leaping",
  "slug": "leaping",
  "former_names": [
    "Terse"
  ],
  "small_logo_thumb_url": "https://bookface-images.s3.amazonaws.com/small_logos/b6b960c84359670b3c32683c8b87f56d98570344.png",
  "website": "https://www.leaping.io/",
  "all_locations": "San Francisco, CA, USA",
  "long_description": "When bad software gets shipped, software companies burn a lot of money and customer trust fixing it. Most software engineers will tell you they spend more time fixing code than writing it, which will only become more true as AI code assistants gain adoption. Leaping autonomously root causes bugs and generates tested code fixes.",
  "one_liner": "Automate bug resolution",
  "team_size": 2,
  "industry": "B2B",
  "subindustry": "B2B -> Engineering, Product and Design",
  "launched_at": 1710320350,
  "tags": [
    "Developer Tools",
    "AI Assistant"
  ],
  "tags_highlighted": [],
  "top_company": false,
  "isHiring": false,
  "nonprofit": false,
  "batch": "W24",
  "status": "Active",
  "industries": [
    "B2B",
    "Engineering, Product and Design"
  ],
  "regions": [
    "United States of America",
    "America / Canada"
  ],
  "stage": "Early",
  "app_video_public": false,
  "demo_day_video_public": false,
  "app_answers": null,
  "question_answers": false,
  "url": "https://www.ycombinator.com/companies/leaping",
  "api": "https://yc-oss.github.io/api/batches/w24/leaping.json"
}
