{
  "id": 29482,
  "name": "TrueClaim",
  "slug": "trueclaim",
  "former_names": [],
  "small_logo_thumb_url": "https://bookface-images.s3.amazonaws.com/small_logos/f5022eca8cc608cc11b6618a6ec690fb93c69218.png",
  "website": "https://www.trytrueclaim.com",
  "all_locations": "Remote",
  "long_description": "TrueClaim processes all payments between healthcare providers and companies that self-fund their insurance. TrueClaim's AI-enabled engine adjudicates and continuously reviews 100% of medical claims to save at least 7% of healthcare costs.",
  "one_liner": "Transparent, AI-powered healthcare TPA.",
  "team_size": 2,
  "industry": "Healthcare",
  "subindustry": "Healthcare",
  "launched_at": 1704498667,
  "tags": [],
  "tags_highlighted": [],
  "top_company": false,
  "isHiring": true,
  "nonprofit": false,
  "batch": "W24",
  "status": "Active",
  "industries": [
    "Healthcare"
  ],
  "regions": [
    "Remote",
    "Fully Remote"
  ],
  "stage": "Early",
  "app_video_public": false,
  "demo_day_video_public": false,
  "app_answers": null,
  "question_answers": true,
  "url": "https://www.ycombinator.com/companies/trueclaim",
  "api": "https://yc-oss.github.io/api/batches/w24/trueclaim.json"
}
