{
  "id": 13213,
  "name": "Plura (formerly Bloom Community)",
  "slug": "plura",
  "former_names": [
    "Together",
    "Bloom (formerly Together)"
  ],
  "small_logo_thumb_url": "https://bookface-images.s3.amazonaws.com/small_logos/382cbea9551900f9780b175a410b6a48e92fadd1.png",
  "website": "https://www.heyplura.com",
  "all_locations": "Oakland, CA, USA",
  "long_description": "Plura (formerly Bloom Community) is a YCombinator backed startup based in Oakland, CA on a mission to use software to bring people together. Plura is a social and dating community that helps you meet new friends and partners organically through shared events and experiences. We partner with local event producers to help you connect and chat with other attendees before and after events. And, with a strong consent culture and referral-based community, we're the safest place to meet new partners and friends. \r\n\r\nThe team is led by Luna Ray. Luna spent 5 years at Facebook, most recently leading viral user growth for Instagram from 700M to past a billion users in two years. ",
  "one_liner": "The social app for edge-of-culture communities",
  "team_size": 5,
  "industry": "Consumer",
  "subindustry": "Consumer -> Social",
  "launched_at": 1583892890,
  "tags": [
    "Community"
  ],
  "tags_highlighted": [],
  "top_company": false,
  "isHiring": false,
  "nonprofit": false,
  "batch": "W20",
  "status": "Active",
  "industries": [
    "Consumer",
    "Social"
  ],
  "regions": [
    "United States of America",
    "America / Canada",
    "Remote",
    "Partly Remote"
  ],
  "stage": "Early",
  "app_video_public": false,
  "demo_day_video_public": false,
  "app_answers": null,
  "question_answers": false,
  "url": "https://www.ycombinator.com/companies/plura",
  "api": "https://yc-oss.github.io/api/batches/w20/plura.json"
}
