{
  "id": 464,
  "name": "Plivo",
  "slug": "plivo",
  "former_names": [],
  "small_logo_thumb_url": "https://bookface-images.s3.amazonaws.com/small_logos/7786f1c9837ea6e7696e60b95c00273cccbf9723.png",
  "website": "https://plivo.com",
  "all_locations": "Austin, TX, USA",
  "long_description": "Plivo's platform helps businesses create and deploy AI Agents for various roles like customer support, marketing engagement, lead qualification across channels like WhatsApp, Voice calls, Web and Mobile Chat, Email & SMS. Plivo's platform powers billions of transactions each year globally for thousands of businesses worldwide like Uber, Meta, Zomato, Deckers etc.",
  "one_liner": "AI Agents for customer engagement on WhatsApp, Voice, Chat & SMS.",
  "team_size": 200,
  "industry": "B2B",
  "subindustry": "B2B -> Engineering, Product and Design",
  "launched_at": 1336694241,
  "tags": [
    "Artificial Intelligence",
    "SMS",
    "AI Assistant"
  ],
  "tags_highlighted": [],
  "top_company": false,
  "isHiring": false,
  "nonprofit": false,
  "batch": "S12",
  "status": "Active",
  "industries": [
    "B2B"
  ],
  "regions": [
    "United States of America",
    "America / Canada",
    "Remote",
    "Partly Remote"
  ],
  "stage": "Growth",
  "app_video_public": false,
  "demo_day_video_public": false,
  "app_answers": null,
  "question_answers": false,
  "url": "https://www.ycombinator.com/companies/plivo",
  "api": "https://yc-oss.github.io/api/batches/s12/plivo.json"
}
