{
  "id": 12573,
  "name": "Bayes",
  "slug": "bayes",
  "former_names": [],
  "small_logo_thumb_url": "https://bookface-images.s3.amazonaws.com/small_logos/6bd9acb006cc7d6fc28381994e1ed810a1d819bb.png",
  "website": "http://bayes.com",
  "all_locations": "San Francisco, CA, USA",
  "long_description": "",
  "one_liner": "",
  "team_size": 4,
  "industry": "B2B",
  "subindustry": "B2B -> Engineering, Product and Design",
  "launched_at": 1633107136,
  "tags": [
    "Data Visualization"
  ],
  "tags_highlighted": [],
  "top_company": false,
  "isHiring": false,
  "nonprofit": false,
  "batch": "Summer 2019",
  "status": "Acquired",
  "industries": [
    "B2B",
    "Engineering, Product and Design"
  ],
  "regions": [
    "United States of America",
    "America / Canada",
    "Remote",
    "Partly Remote"
  ],
  "stage": "Early",
  "app_video_public": false,
  "demo_day_video_public": false,
  "app_answers": null,
  "question_answers": false,
  "url": "https://www.ycombinator.com/companies/bayes",
  "api": "https://yc-oss.github.io/api/batches/summer-2019/bayes.json"
}
