{
  "id": 24038,
  "name": "FrontPage",
  "slug": "frontpage",
  "former_names": [
    "Crowdware Labs Private Limited"
  ],
  "small_logo_thumb_url": "https://bookface-images.s3.amazonaws.com/small_logos/29ac95e715a7bf8e21b677a36c6d3cebf4e933ad.png",
  "website": "https://front.page",
  "all_locations": "Bengaluru, KA, India",
  "long_description": "FrontPage has built a community for financial market traders in India. The community has more than 1M monthly active users.\r\n\r\nNow building a new stock trading platform for India, leveraging AI advances. \r\n\r\n\r\n\r\n",
  "one_liner": "AI first stock trading platform for India",
  "team_size": 24,
  "industry": "Fintech",
  "subindustry": "Fintech -> Asset Management",
  "launched_at": 1627473725,
  "tags": [
    "Fintech",
    "Community",
    "AI"
  ],
  "tags_highlighted": [],
  "top_company": false,
  "isHiring": true,
  "nonprofit": false,
  "batch": "S21",
  "status": "Active",
  "industries": [
    "Fintech",
    "Asset Management"
  ],
  "regions": [
    "India",
    "South Asia",
    "Remote",
    "Partly Remote"
  ],
  "stage": "Early",
  "app_video_public": false,
  "demo_day_video_public": false,
  "app_answers": null,
  "question_answers": false,
  "url": "https://www.ycombinator.com/companies/frontpage",
  "api": "https://yc-oss.github.io/api/batches/s21/frontpage.json"
}
