{
  "id": 24195,
  "name": "Tarsal",
  "slug": "tarsal",
  "former_names": [
    "V-diff",
    "vdiff"
  ],
  "small_logo_thumb_url": "https://bookface-images.s3.amazonaws.com/small_logos/75747b61e59eadbd8831c406fbe1beed2fd4957b.png",
  "website": "https://www.tarsal.co/",
  "all_locations": "New York, NY, USA; San Francisco, CA, USA; Remote",
  "long_description": "Tarsal is a data pipeline custom built for security teams. As security data grows 25% year over year, security teams desperately need access to best-in-class data infrastructure. Tarsal bridges the gap between the modern data stack and security teams, pioneering the modern security data stack. \r\n",
  "one_liner": "Data pipeline for your security data lake.",
  "team_size": 10,
  "industry": "B2B",
  "subindustry": "B2B -> Security",
  "launched_at": 1680491615,
  "tags": [
    "B2B",
    "Cybersecurity",
    "Big Data",
    "Data Engineering"
  ],
  "tags_highlighted": [],
  "top_company": false,
  "isHiring": true,
  "nonprofit": false,
  "batch": "S21",
  "status": "Active",
  "industries": [
    "B2B",
    "Security"
  ],
  "regions": [
    "United States of America",
    "America / Canada",
    "Remote",
    "Fully Remote"
  ],
  "stage": "Early",
  "app_video_public": false,
  "demo_day_video_public": false,
  "app_answers": null,
  "question_answers": false,
  "url": "https://www.ycombinator.com/companies/tarsal",
  "api": "https://yc-oss.github.io/api/batches/s21/tarsal.json"
}
